[{"user":1,"id":"759e9b25997788d7cd56","model":"Web","screen_height":0,"screen_width":0,"sdk":1,"type":"WebDevice"},{"user":2,"id":"27fa29efbb4a33ca8ac9","model":"Web","screen_height":0,"screen_width":0,"sdk":1,"type":"WebDevice"},{"user":3,"id":"e4067ffef74e39d50e4a","model":"Web","screen_height":0,"screen_width":0,"sdk":1,"type":"WebDevice"},{"user":4,"id":"764091a57c524b7335a6","model":"Web","screen_height":0,"screen_width":0,"sdk":1,"type":"WebDevice"},{"user":5,"id":"85adf744d723028bf740","model":"Web","screen_height":0,"screen_width":0,"sdk":1,"type":"WebDevice"}]
